lixplore/__init__.py
lixplore/__main__.py
lixplore/cli.py
lixplore/commands.py
lixplore/dispatcher.py
lixplore/search.py
lixplore/sources/__init__.py
lixplore/sources/arxiv.py
lixplore/sources/crossref.py
lixplore/sources/doaj.py
lixplore/sources/europepmc.py
lixplore/sources/pubmed.py
lixplore/templates/__init__.py
lixplore/templates/ieee.json
lixplore/templates/nature.json
lixplore/templates/science.json
lixplore/utils/annotations.py
lixplore/utils/cache.py
lixplore/utils/citations.py
lixplore/utils/custom_apis.py
lixplore/utils/enhanced_tui.py
lixplore/utils/enrichment.py
lixplore/utils/export.py
lixplore/utils/interactive_tui.py
lixplore/utils/pdf_downloader.py
lixplore/utils/profiles.py
lixplore/utils/reference_managers.py
lixplore/utils/shell_mode.py
lixplore/utils/statistics.py
lixplore/utils/template_engine.py
lixplore/utils/terminal.py
lixplore/utils/wizard_mode.py
lixplore_cli-1.0.1.dist-info/licenses/LICENSE
lixplore_cli-1.0.1.dist-info/METADATA
lixplore_cli-1.0.1.dist-info/WHEEL
lixplore_cli-1.0.1.dist-info/entry_points.txt
lixplore_cli-1.0.1.dist-info/top_level.txt
lixplore_cli-1.0.1.dist-info/RECORD
