Metadata-Version: 2.4
Name: lixplore-cli
Version: 1.0.1
Summary: Academic Literature Search & Export CLI Tool
Home-page: https://github.com/pryndor/Lixplore_cli
Author: Pryndor
Author-email: Balasubramanian Periannan <balathepharmacist@gmail.com>
Maintainer-email: Balasubramanian Periannan <balathepharmacist@gmail.com>
License: MIT
Project-URL: Homepage, https://github.com/pryndor/Lixplore_cli
Project-URL: Documentation, https://pryndor.github.io/Lixplore_cli/
Project-URL: Repository, https://github.com/pryndor/Lixplore_cli
Project-URL: Bug Tracker, https://github.com/pryndor/Lixplore_cli/issues
Keywords: literature,search,academic,pubmed,arxiv,crossref,research,papers,export,bibliography,scientific,citations
Classifier: Development Status :: 5 - Production/Stable
Classifier: Intended Audience :: Science/Research
Classifier: Intended Audience :: Education
Classifier: Intended Audience :: Healthcare Industry
Classifier: Topic :: Scientific/Engineering :: Information Analysis
Classifier: Topic :: Scientific/Engineering :: Medical Science Apps.
Classifier: Topic :: Text Processing :: General
Classifier: License :: OSI Approved :: MIT License
Classifier: Programming Language :: Python :: 3
Classifier: Programming Language :: Python :: 3.8
Classifier: Programming Language :: Python :: 3.9
Classifier: Programming Language :: Python :: 3.10
Classifier: Programming Language :: Python :: 3.11
Classifier: Programming Language :: Python :: 3.12
Classifier: Operating System :: OS Independent
Classifier: Operating System :: POSIX :: Linux
Classifier: Operating System :: MacOS
Classifier: Operating System :: Microsoft :: Windows
Classifier: Environment :: Console
Requires-Python: >=3.8
License-File: LICENSE
Requires-Dist: biopython>=1.79
Requires-Dist: requests>=2.25.0
Requires-Dist: litstudy>=1.0.0
Requires-Dist: openpyxl>=3.0.0
Provides-Extra: dev
Requires-Dist: pytest>=6.0; extra == "dev"
Requires-Dist: pytest-cov; extra == "dev"
Requires-Dist: black; extra == "dev"
Requires-Dist: flake8; extra == "dev"
Requires-Dist: mypy; extra == "dev"
Dynamic: author
Dynamic: home-page
Dynamic: license-file
Dynamic: requires-python
